buycoins_sdk/__init__.py
buycoins_sdk/client/__init__.py
buycoins_sdk/client/client.py
buycoins_sdk/commons/__init__.py
buycoins_sdk/commons/enums.py
buycoins_sdk/commons/errors.py
buycoins_sdk/commons/gql_fields.py
buycoins_sdk/commons/utils.py
buycoins_sdk/core/__init__.py
buycoins_sdk/core/main_buycoins_sdk.py
buycoins_sdk/core/types.py
buycoins_sdk/tests/__init__.py
buycoins_sdk/tests/client/__init__.py
buycoins_sdk/tests/client/fixtures.py
buycoins_sdk/tests/client/test_client.py
buycoins_sdk/tests/core/__init__.py
buycoins_sdk/tests/core/test_main_buycoins_sdk.py
buycoins_sdk/tests/core/test_types.py
Buycoins_Python_SDK-0.0.1.dist-info/LICENSE
Buycoins_Python_SDK-0.0.1.dist-info/METADATA
Buycoins_Python_SDK-0.0.1.dist-info/WHEEL
Buycoins_Python_SDK-0.0.1.dist-info/top_level.txt
Buycoins_Python_SDK-0.0.1.dist-info/RECORD
