Metadata-Version: 2.1
Name: Buycoins-Python-SDK
Version: 0.0.1
Summary: A Python SDK for Buycoins
Home-page: https://github.com/GoZaddy/buycoins_sdk
Author: Faruq Yusuff
Author-email: faruqyusuff437@gmail.com
License: MIT
Keywords: sdk buycoins
Platform: UNKNOWN
Classifier: Development Status :: 4 - Beta
Classifier: License :: OSI Approved :: MIT License
Classifier: Intended Audience :: Developers
Requires-Python: >=3.6
Requires-Dist: python-graphql-client (==0.4.2)
Requires-Dist: python-dotenv (==0.15.0)
Requires-Dist: requests (~=2.25.1)
